<?xml version="1.0" encoding="utf-8"?>
<annotations>
  <version>1.1</version>
  <meta>
    <task>
      <size>129</size>
    </task>
  </meta>
  <track id="5002" label="person">
    <box frame="0" outside="0" occluded="0" keyframe="1" xtl="813.81" ytl="488.61" xbr="1121.21" ybr="1077.11">
    </box>
    <box frame="1" outside="0" occluded="0" keyframe="1" xtl="781.86" ytl="483.25" xbr="1090.56" ybr="1076.51">
    </box>
    <box frame="2" outside="0" occluded="0" keyframe="1" xtl="768.53" ytl="474.79" xbr="1079.79" ybr="1076.13">
    </box>
    <box frame="3" outside="0" occluded="0" keyframe="1" xtl="764.07" ytl="466.62" xbr="1078.60" ybr="1076.86">
    </box>
    <box frame="4" outside="0" occluded="0" keyframe="1" xtl="780.81" ytl="458.54" xbr="1103.90" ybr="1076.41">
    </box>
    <box frame="5" outside="0" occluded="0" keyframe="1" xtl="774.12" ytl="449.60" xbr="1101.48" ybr="1076.19">
    </box>
    <box frame="6" outside="0" occluded="0" keyframe="1" xtl="787.62" ytl="439.96" xbr="1124.07" ybr="1076.11">
    </box>
    <box frame="7" outside="0" occluded="0" keyframe="1" xtl="773.69" ytl="429.80" xbr="1112.73" ybr="1075.41">
    </box>
    <box frame="8" outside="0" occluded="0" keyframe="1" xtl="767.89" ytl="418.63" xbr="1108.92" ybr="1075.24">
    </box>
    <box frame="9" outside="0" occluded="0" keyframe="1" xtl="776.86" ytl="408.32" xbr="1115.78" ybr="1074.73">
    </box>
    <box frame="10" outside="0" occluded="0" keyframe="1" xtl="777.72" ytl="394.86" xbr="1115.74" ybr="1074.31">
    </box>
    <box frame="11" outside="0" occluded="0" keyframe="1" xtl="773.45" ytl="382.42" xbr="1111.21" ybr="1074.53">
    </box>
    <box frame="12" outside="0" occluded="0" keyframe="1" xtl="777.17" ytl="372.02" xbr="1111.28" ybr="1072.39">
    </box>
    <box frame="13" outside="0" occluded="0" keyframe="1" xtl="786.96" ytl="359.82" xbr="1121.58" ybr="1072.65">
    </box>
    <box frame="14" outside="0" occluded="0" keyframe="1" xtl="782.55" ytl="346.65" xbr="1117.09" ybr="1067.24">
    </box>
    <box frame="15" outside="0" occluded="0" keyframe="1" xtl="785.29" ytl="337.70" xbr="1107.93" ybr="1041.95">
    </box>
    <box frame="16" outside="0" occluded="0" keyframe="1" xtl="796.04" ytl="329.85" xbr="1103.54" ybr="1013.39">
    </box>
    <box frame="17" outside="0" occluded="0" keyframe="1" xtl="806.67" ytl="323.81" xbr="1100.49" ybr="985.30">
    </box>
    <box frame="18" outside="0" occluded="0" keyframe="1" xtl="813.49" ytl="318.00" xbr="1097.02" ybr="963.73">
    </box>
    <box frame="19" outside="0" occluded="0" keyframe="1" xtl="812.75" ytl="312.10" xbr="1093.10" ybr="954.63">
    </box>
    <box frame="20" outside="0" occluded="0" keyframe="1" xtl="813.82" ytl="303.38" xbr="1094.78" ybr="951.95">
    </box>
    <box frame="21" outside="0" occluded="0" keyframe="1" xtl="819.76" ytl="298.81" xbr="1099.45" ybr="951.05">
    </box>
    <box frame="22" outside="0" occluded="0" keyframe="1" xtl="825.10" ytl="296.99" xbr="1102.27" ybr="950.30">
    </box>
    <box frame="23" outside="0" occluded="0" keyframe="1" xtl="832.01" ytl="290.62" xbr="1107.71" ybr="949.19">
    </box>
    <box frame="24" outside="0" occluded="0" keyframe="1" xtl="837.74" ytl="287.20" xbr="1111.08" ybr="949.30">
    </box>
    <box frame="25" outside="0" occluded="0" keyframe="1" xtl="846.11" ytl="280.65" xbr="1116.75" ybr="947.15">
    </box>
    <box frame="26" outside="0" occluded="0" keyframe="1" xtl="853.94" ytl="273.59" xbr="1120.69" ybr="941.95">
    </box>
    <box frame="27" outside="0" occluded="0" keyframe="1" xtl="858.47" ytl="265.25" xbr="1120.69" ybr="930.67">
    </box>
    <box frame="28" outside="0" occluded="0" keyframe="1" xtl="865.23" ytl="255.22" xbr="1121.91" ybr="913.51">
    </box>
    <box frame="29" outside="0" occluded="0" keyframe="1" xtl="876.25" ytl="247.43" xbr="1123.00" ybr="887.08">
    </box>
    <box frame="30" outside="0" occluded="0" keyframe="1" xtl="877.78" ytl="236.86" xbr="1118.19" ybr="859.93">
    </box>
    <box frame="31" outside="0" occluded="0" keyframe="1" xtl="880.56" ytl="227.42" xbr="1116.64" ybr="837.30">
    </box>
    <box frame="32" outside="0" occluded="0" keyframe="1" xtl="886.33" ytl="219.75" xbr="1118.96" ybr="818.94">
    </box>
    <box frame="33" outside="0" occluded="0" keyframe="1" xtl="879.38" ytl="209.49" xbr="1114.68" ybr="805.91">
    </box>
    <box frame="34" outside="0" occluded="0" keyframe="1" xtl="881.63" ytl="201.33" xbr="1117.55" ybr="792.72">
    </box>
    <box frame="35" outside="0" occluded="0" keyframe="1" xtl="886.80" ytl="194.89" xbr="1125.64" ybr="784.00">
    </box>
    <box frame="36" outside="0" occluded="0" keyframe="1" xtl="890.28" ytl="196.21" xbr="1129.90" ybr="780.74">
    </box>
    <box frame="37" outside="0" occluded="0" keyframe="1" xtl="887.08" ytl="192.33" xbr="1127.89" ybr="778.14">
    </box>
    <box frame="38" outside="0" occluded="0" keyframe="1" xtl="880.60" ytl="189.28" xbr="1122.53" ybr="778.21">
    </box>
    <box frame="39" outside="0" occluded="0" keyframe="1" xtl="874.02" ytl="190.08" xbr="1115.91" ybr="778.45">
    </box>
    <box frame="40" outside="0" occluded="0" keyframe="1" xtl="872.37" ytl="187.38" xbr="1115.11" ybr="777.85">
    </box>
    <box frame="41" outside="0" occluded="0" keyframe="1" xtl="868.85" ytl="180.02" xbr="1114.45" ybr="776.12">
    </box>
    <box frame="42" outside="0" occluded="0" keyframe="1" xtl="864.74" ytl="168.88" xbr="1114.05" ybr="775.08">
    </box>
    <box frame="43" outside="0" occluded="0" keyframe="1" xtl="859.72" ytl="147.92" xbr="1115.25" ybr="772.95">
    </box>
    <box frame="44" outside="0" occluded="0" keyframe="1" xtl="857.73" ytl="132.35" xbr="1116.93" ybr="771.07">
    </box>
    <box frame="45" outside="0" occluded="0" keyframe="1" xtl="858.42" ytl="127.08" xbr="1117.25" ybr="769.70">
    </box>
    <box frame="46" outside="0" occluded="0" keyframe="1" xtl="860.68" ytl="126.15" xbr="1117.39" ybr="767.77">
    </box>
    <box frame="47" outside="0" occluded="0" keyframe="1" xtl="862.05" ytl="125.99" xbr="1116.68" ybr="767.14">
    </box>
    <box frame="48" outside="0" occluded="0" keyframe="1" xtl="863.04" ytl="127.44" xbr="1114.74" ybr="766.96">
    </box>
    <box frame="49" outside="0" occluded="0" keyframe="1" xtl="864.47" ytl="128.86" xbr="1113.32" ybr="766.92">
    </box>
    <box frame="50" outside="0" occluded="0" keyframe="1" xtl="863.95" ytl="130.20" xbr="1109.99" ybr="767.03">
    </box>
    <box frame="51" outside="0" occluded="0" keyframe="1" xtl="862.81" ytl="131.21" xbr="1106.21" ybr="767.44">
    </box>
    <box frame="52" outside="0" occluded="0" keyframe="1" xtl="861.21" ytl="131.65" xbr="1101.67" ybr="767.82">
    </box>
    <box frame="53" outside="0" occluded="0" keyframe="1" xtl="860.86" ytl="129.95" xbr="1099.25" ybr="768.24">
    </box>
    <box frame="54" outside="0" occluded="0" keyframe="1" xtl="860.67" ytl="127.63" xbr="1097.48" ybr="769.77">
    </box>
    <box frame="55" outside="0" occluded="0" keyframe="1" xtl="861.05" ytl="124.01" xbr="1096.54" ybr="770.65">
    </box>
    <box frame="56" outside="0" occluded="0" keyframe="1" xtl="862.86" ytl="119.57" xbr="1096.87" ybr="771.07">
    </box>
    <box frame="57" outside="0" occluded="0" keyframe="1" xtl="862.37" ytl="115.46" xbr="1094.87" ybr="771.22">
    </box>
    <box frame="58" outside="0" occluded="0" keyframe="1" xtl="865.59" ytl="134.08" xbr="1088.87" ybr="769.69">
    </box>
    <box frame="59" outside="0" occluded="0" keyframe="1" xtl="867.51" ytl="154.37" xbr="1082.21" ybr="768.13">
    </box>
    <box frame="60" outside="0" occluded="0" keyframe="1" xtl="865.98" ytl="143.35" xbr="1081.78" ybr="764.75">
    </box>
    <box frame="61" outside="0" occluded="0" keyframe="1" xtl="868.91" ytl="159.71" xbr="1077.76" ybr="761.87">
    </box>
    <box frame="62" outside="0" occluded="0" keyframe="1" xtl="869.14" ytl="168.44" xbr="1073.92" ybr="758.76">
    </box>
    <box frame="63" outside="0" occluded="0" keyframe="1" xtl="867.69" ytl="171.64" xbr="1071.02" ybr="757.21">
    </box>
    <box frame="64" outside="0" occluded="0" keyframe="1" xtl="866.08" ytl="173.44" xbr="1068.83" ybr="755.99">
    </box>
    <box frame="65" outside="0" occluded="0" keyframe="1" xtl="865.25" ytl="174.24" xbr="1068.18" ybr="755.63">
    </box>
    <box frame="66" outside="0" occluded="0" keyframe="1" xtl="864.86" ytl="174.24" xbr="1068.06" ybr="754.40">
    </box>
    <box frame="67" outside="0" occluded="0" keyframe="1" xtl="864.51" ytl="173.31" xbr="1068.79" ybr="754.57">
    </box>
    <box frame="68" outside="0" occluded="0" keyframe="1" xtl="863.52" ytl="172.21" xbr="1069.02" ybr="755.17">
    </box>
    <box frame="69" outside="0" occluded="0" keyframe="1" xtl="862.28" ytl="170.24" xbr="1069.10" ybr="755.57">
    </box>
    <box frame="70" outside="0" occluded="0" keyframe="1" xtl="860.03" ytl="168.93" xbr="1068.20" ybr="756.20">
    </box>
    <box frame="71" outside="0" occluded="0" keyframe="1" xtl="859.21" ytl="168.06" xbr="1068.75" ybr="757.89">
    </box>
    <box frame="72" outside="0" occluded="0" keyframe="1" xtl="858.44" ytl="166.58" xbr="1069.22" ybr="758.79">
    </box>
    <box frame="73" outside="0" occluded="0" keyframe="1" xtl="858.73" ytl="165.66" xbr="1070.09" ybr="759.34">
    </box>
    <box frame="74" outside="0" occluded="0" keyframe="1" xtl="858.66" ytl="164.20" xbr="1070.71" ybr="759.69">
    </box>
    <box frame="75" outside="0" occluded="0" keyframe="1" xtl="857.76" ytl="162.07" xbr="1071.02" ybr="760.70">
    </box>
    <box frame="76" outside="0" occluded="0" keyframe="1" xtl="857.37" ytl="160.08" xbr="1071.46" ybr="761.05">
    </box>
    <box frame="77" outside="0" occluded="0" keyframe="1" xtl="855.53" ytl="159.03" xbr="1070.44" ybr="761.54">
    </box>
    <box frame="78" outside="0" occluded="0" keyframe="1" xtl="855.00" ytl="157.50" xbr="1070.63" ybr="761.46">
    </box>
    <box frame="79" outside="0" occluded="0" keyframe="1" xtl="855.15" ytl="156.79" xbr="1071.26" ybr="761.99">
    </box>
    <box frame="80" outside="0" occluded="0" keyframe="1" xtl="852.72" ytl="152.94" xbr="1070.88" ybr="762.06">
    </box>
    <box frame="81" outside="0" occluded="0" keyframe="1" xtl="851.80" ytl="154.21" xbr="1070.36" ybr="762.80">
    </box>
    <box frame="82" outside="0" occluded="0" keyframe="1" xtl="851.23" ytl="155.34" xbr="1070.24" ybr="763.33">
    </box>
    <box frame="83" outside="0" occluded="0" keyframe="1" xtl="853.74" ytl="155.16" xbr="1072.75" ybr="763.63">
    </box>
    <box frame="84" outside="0" occluded="0" keyframe="1" xtl="857.46" ytl="156.11" xbr="1075.28" ybr="763.50">
    </box>
    <box frame="85" outside="0" occluded="0" keyframe="1" xtl="854.03" ytl="159.75" xbr="1071.30" ybr="763.31">
    </box>
    <box frame="86" outside="0" occluded="0" keyframe="1" xtl="851.51" ytl="162.86" xbr="1068.68" ybr="762.58">
    </box>
    <box frame="87" outside="0" occluded="0" keyframe="1" xtl="850.74" ytl="166.44" xbr="1067.55" ybr="761.28">
    </box>
    <box frame="88" outside="0" occluded="0" keyframe="1" xtl="851.64" ytl="170.72" xbr="1067.52" ybr="759.29">
    </box>
    <box frame="89" outside="0" occluded="0" keyframe="1" xtl="852.72" ytl="173.61" xbr="1068.10" ybr="757.34">
    </box>
    <box frame="90" outside="0" occluded="0" keyframe="1" xtl="853.25" ytl="175.98" xbr="1068.33" ybr="755.65">
    </box>
    <box frame="91" outside="0" occluded="0" keyframe="1" xtl="852.29" ytl="178.89" xbr="1067.05" ybr="753.84">
    </box>
    <box frame="92" outside="0" occluded="0" keyframe="1" xtl="852.10" ytl="181.57" xbr="1067.00" ybr="754.16">
    </box>
    <box frame="93" outside="0" occluded="0" keyframe="1" xtl="850.05" ytl="183.94" xbr="1065.12" ybr="755.50">
    </box>
    <box frame="94" outside="0" occluded="0" keyframe="1" xtl="847.40" ytl="186.53" xbr="1063.22" ybr="760.03">
    </box>
    <box frame="95" outside="0" occluded="0" keyframe="1" xtl="846.95" ytl="189.99" xbr="1063.52" ybr="768.31">
    </box>
    <box frame="96" outside="0" occluded="0" keyframe="1" xtl="845.31" ytl="195.18" xbr="1062.63" ybr="777.92">
    </box>
    <box frame="97" outside="0" occluded="0" keyframe="1" xtl="844.92" ytl="201.48" xbr="1063.03" ybr="788.22">
    </box>
    <box frame="98" outside="0" occluded="0" keyframe="1" xtl="845.07" ytl="207.26" xbr="1065.07" ybr="799.84">
    </box>
    <box frame="99" outside="0" occluded="0" keyframe="1" xtl="845.15" ytl="211.85" xbr="1067.50" ybr="811.38">
    </box>
    <box frame="100" outside="0" occluded="0" keyframe="1" xtl="845.20" ytl="220.19" xbr="1068.92" ybr="823.52">
    </box>
    <box frame="101" outside="0" occluded="0" keyframe="1" xtl="845.20" ytl="227.06" xbr="1072.15" ybr="838.79">
    </box>
    <box frame="102" outside="0" occluded="0" keyframe="1" xtl="846.63" ytl="235.06" xbr="1074.99" ybr="850.12">
    </box>
    <box frame="103" outside="0" occluded="0" keyframe="1" xtl="847.33" ytl="244.02" xbr="1077.92" ybr="864.96">
    </box>
    <box frame="104" outside="0" occluded="0" keyframe="1" xtl="846.75" ytl="251.98" xbr="1080.27" ybr="881.05">
    </box>
    <box frame="105" outside="0" occluded="0" keyframe="1" xtl="847.09" ytl="259.35" xbr="1084.02" ybr="897.90">
    </box>
    <box frame="106" outside="0" occluded="0" keyframe="1" xtl="849.27" ytl="268.51" xbr="1086.91" ybr="909.30">
    </box>
    <box frame="107" outside="0" occluded="0" keyframe="1" xtl="852.14" ytl="275.08" xbr="1090.41" ybr="916.96">
    </box>
    <box frame="108" outside="0" occluded="0" keyframe="1" xtl="853.15" ytl="278.26" xbr="1092.53" ybr="920.75">
    </box>
    <box frame="109" outside="0" occluded="0" keyframe="1" xtl="853.30" ytl="282.87" xbr="1093.33" ybr="923.06">
    </box>
    <box frame="110" outside="0" occluded="0" keyframe="1" xtl="850.33" ytl="287.29" xbr="1091.24" ybr="922.39">
    </box>
    <box frame="111" outside="0" occluded="0" keyframe="1" xtl="847.58" ytl="291.09" xbr="1089.99" ybr="921.78">
    </box>
    <box frame="112" outside="0" occluded="0" keyframe="1" xtl="843.73" ytl="295.63" xbr="1088.75" ybr="923.14">
    </box>
    <box frame="113" outside="0" occluded="0" keyframe="1" xtl="838.52" ytl="298.09" xbr="1086.61" ybr="923.50">
    </box>
    <box frame="114" outside="0" occluded="0" keyframe="1" xtl="832.18" ytl="301.64" xbr="1083.01" ybr="923.31">
    </box>
    <box frame="115" outside="0" occluded="0" keyframe="1" xtl="826.61" ytl="307.35" xbr="1078.53" ybr="922.16">
    </box>
    <box frame="116" outside="0" occluded="0" keyframe="1" xtl="829.78" ytl="314.25" xbr="1080.00" ybr="921.01">
    </box>
    <box frame="117" outside="0" occluded="0" keyframe="1" xtl="818.10" ytl="318.36" xbr="1071.16" ybr="920.73">
    </box>
    <box frame="118" outside="0" occluded="0" keyframe="1" xtl="827.14" ytl="324.93" xbr="1081.41" ybr="931.89">
    </box>
    <box frame="119" outside="0" occluded="0" keyframe="1" xtl="823.09" ytl="331.77" xbr="1083.21" ybr="952.78">
    </box>
    <box frame="120" outside="0" occluded="0" keyframe="1" xtl="803.40" ytl="341.36" xbr="1073.50" ybr="978.88">
    </box>
    <box frame="121" outside="0" occluded="0" keyframe="1" xtl="792.05" ytl="351.47" xbr="1071.18" ybr="1007.06">
    </box>
    <box frame="122" outside="0" occluded="0" keyframe="1" xtl="785.88" ytl="360.91" xbr="1071.36" ybr="1031.74">
    </box>
    <box frame="123" outside="0" occluded="0" keyframe="1" xtl="781.89" ytl="371.28" xbr="1072.58" ybr="1058.18">
    </box>
    <box frame="124" outside="0" occluded="0" keyframe="1" xtl="780.05" ytl="381.60" xbr="1069.99" ybr="1071.35">
    </box>
    <box frame="125" outside="0" occluded="0" keyframe="1" xtl="778.85" ytl="391.61" xbr="1064.54" ybr="1076.02">
    </box>
    <box frame="126" outside="0" occluded="0" keyframe="1" xtl="774.68" ytl="399.73" xbr="1056.26" ybr="1078.25">
    </box>
    <box frame="127" outside="0" occluded="0" keyframe="1" xtl="769.75" ytl="406.79" xbr="1046.63" ybr="1078.12">
    </box>
    <box frame="128" outside="0" occluded="0" keyframe="1" xtl="765.12" ytl="413.13" xbr="1037.21" ybr="1078.10">
    </box>
  </track>
  <track id="5004" label="person">
    <box frame="0" outside="0" occluded="0" keyframe="1" xtl="881.79" ytl="49.73" xbr="1070.85" ybr="579.42">
    </box>
    <box frame="1" outside="0" occluded="0" keyframe="1" xtl="903.26" ytl="17.38" xbr="1084.45" ybr="526.53">
    </box>
    <box frame="2" outside="0" occluded="0" keyframe="1" xtl="911.75" ytl="7.29" xbr="1087.88" ybr="502.65">
    </box>
    <box frame="3" outside="0" occluded="0" keyframe="1" xtl="914.72" ytl="4.60" xbr="1088.58" ybr="493.88">
    </box>
    <box frame="4" outside="0" occluded="0" keyframe="1" xtl="916.72" ytl="4.84" xbr="1086.33" ybr="480.44">
    </box>
    <box frame="5" outside="0" occluded="0" keyframe="1" xtl="915.93" ytl="5.99" xbr="1084.81" ybr="477.54">
    </box>
    <box frame="6" outside="0" occluded="0" keyframe="1" xtl="915.63" ytl="7.85" xbr="1083.29" ybr="473.17">
    </box>
    <box frame="7" outside="0" occluded="0" keyframe="1" xtl="915.10" ytl="10.93" xbr="1081.98" ybr="470.77">
    </box>
    <box frame="8" outside="0" occluded="0" keyframe="1" xtl="914.62" ytl="15.13" xbr="1080.88" ybr="469.54">
    </box>
    <box frame="9" outside="0" occluded="0" keyframe="1" xtl="913.96" ytl="20.26" xbr="1079.89" ybr="469.52">
    </box>
    <box frame="10" outside="0" occluded="0" keyframe="1" xtl="912.41" ytl="25.40" xbr="1079.56" ybr="473.87">
    </box>
    <box frame="11" outside="0" occluded="0" keyframe="1" xtl="911.57" ytl="30.85" xbr="1078.62" ybr="474.40">
    </box>
    <box frame="12" outside="0" occluded="0" keyframe="1" xtl="911.35" ytl="35.57" xbr="1078.03" ybr="473.02">
    </box>
    <box frame="13" outside="0" occluded="0" keyframe="1" xtl="909.68" ytl="40.49" xbr="1076.13" ybr="471.36">
    </box>
    <box frame="14" outside="0" occluded="0" keyframe="1" xtl="907.31" ytl="44.32" xbr="1074.17" ybr="469.68">
    </box>
    <box frame="15" outside="0" occluded="0" keyframe="1" xtl="904.19" ytl="47.57" xbr="1072.23" ybr="469.09">
    </box>
    <box frame="16" outside="0" occluded="0" keyframe="1" xtl="901.78" ytl="49.11" xbr="1071.35" ybr="468.35">
    </box>
    <box frame="17" outside="0" occluded="0" keyframe="1" xtl="900.65" ytl="50.19" xbr="1069.72" ybr="461.16">
    </box>
    <box frame="18" outside="0" occluded="0" keyframe="1" xtl="896.46" ytl="51.84" xbr="1069.91" ybr="467.45">
    </box>
    <box frame="19" outside="0" occluded="0" keyframe="1" xtl="871.79" ytl="52.00" xbr="1088.90" ybr="578.41">
    </box>
    <box frame="20" outside="0" occluded="0" keyframe="1" xtl="874.57" ytl="54.10" xbr="1070.44" ybr="513.20">
    </box>
    <box frame="21" outside="0" occluded="0" keyframe="1" xtl="876.36" ytl="55.13" xbr="1063.79" ybr="482.25">
    </box>
    <box frame="22" outside="0" occluded="0" keyframe="1" xtl="873.09" ytl="57.75" xbr="1058.04" ybr="464.90">
    </box>
    <box frame="23" outside="0" occluded="0" keyframe="1" xtl="850.11" ytl="59.28" xbr="1087.17" ybr="587.29">
    </box>
    <box frame="24" outside="0" occluded="0" keyframe="1" xtl="859.85" ytl="61.46" xbr="1079.39" ybr="544.54">
    </box>
    <box frame="25" outside="0" occluded="0" keyframe="1" xtl="873.07" ytl="63.97" xbr="1067.75" ybr="479.66">
    </box>
    <box frame="26" outside="0" occluded="0" keyframe="1" xtl="878.74" ytl="69.00" xbr="1062.79" ybr="448.66">
    </box>
    <box frame="27" outside="0" occluded="0" keyframe="1" xtl="882.28" ytl="73.56" xbr="1061.11" ybr="428.64">
    </box>
    <box frame="28" outside="0" occluded="0" keyframe="1" xtl="884.57" ytl="79.13" xbr="1060.50" ybr="412.98">
    </box>
    <box frame="29" outside="0" occluded="0" keyframe="1" xtl="884.76" ytl="83.75" xbr="1063.30" ybr="407.57">
    </box>
    <box frame="30" outside="0" occluded="0" keyframe="1" xtl="885.01" ytl="87.73" xbr="1070.10" ybr="409.03">
    </box>
    <box frame="31" outside="0" occluded="0" keyframe="1" xtl="885.28" ytl="91.21" xbr="1081.39" ybr="417.55">
    </box>
    <box frame="32" outside="0" occluded="0" keyframe="1" xtl="890.36" ytl="94.28" xbr="1088.15" ybr="406.65">
    </box>
    <box frame="33" outside="0" occluded="0" keyframe="1" xtl="892.27" ytl="95.96" xbr="1104.69" ybr="418.43">
    </box>
    <box frame="34" outside="0" occluded="0" keyframe="1" xtl="901.44" ytl="98.39" xbr="1114.24" ybr="408.30">
    </box>
    <box frame="35" outside="0" occluded="0" keyframe="1" xtl="877.64" ytl="101.32" xbr="1153.43" ybr="506.14">
    </box>
    <box frame="36" outside="0" occluded="0" keyframe="1" xtl="902.70" ytl="103.08" xbr="1136.31" ybr="429.57">
    </box>
    <box frame="37" outside="0" occluded="0" keyframe="1" xtl="919.61" ytl="105.79" xbr="1127.21" ybr="384.02">
    </box>
    <box frame="38" outside="0" occluded="0" keyframe="1" xtl="921.04" ytl="109.34" xbr="1118.59" ybr="362.41">
    </box>
    <box frame="39" outside="0" occluded="0" keyframe="1" xtl="918.86" ytl="112.33" xbr="1115.24" ybr="355.29">
    </box>
    <box frame="40" outside="0" occluded="0" keyframe="1" xtl="904.84" ytl="115.71" xbr="1100.48" ybr="352.45">
    </box>
    <box frame="41" outside="0" occluded="0" keyframe="1" xtl="897.50" ytl="118.56" xbr="1097.22" ybr="352.92">
    </box>
    <box frame="68" outside="0" occluded="0" keyframe="1" xtl="907.24" ytl="110.40" xbr="1106.89" ybr="367.95">
    </box>
    <box frame="69" outside="0" occluded="0" keyframe="1" xtl="913.25" ytl="111.99" xbr="1100.78" ybr="370.36">
    </box>
    <box frame="70" outside="0" occluded="0" keyframe="1" xtl="916.91" ytl="114.40" xbr="1095.24" ybr="371.72">
    </box>
    <box frame="71" outside="0" occluded="0" keyframe="1" xtl="919.33" ytl="116.71" xbr="1090.80" ybr="371.93">
    </box>
    <box frame="72" outside="0" occluded="0" keyframe="1" xtl="921.75" ytl="119.97" xbr="1087.83" ybr="373.87">
    </box>
    <box frame="73" outside="0" occluded="0" keyframe="1" xtl="923.42" ytl="122.79" xbr="1085.46" ybr="375.94">
    </box>
    <box frame="74" outside="0" occluded="0" keyframe="1" xtl="925.47" ytl="125.29" xbr="1083.86" ybr="377.49">
    </box>
    <box frame="75" outside="0" occluded="0" keyframe="1" xtl="926.92" ytl="127.89" xbr="1082.32" ybr="379.25">
    </box>
    <box frame="76" outside="0" occluded="0" keyframe="1" xtl="927.05" ytl="129.91" xbr="1080.96" ybr="382.69">
    </box>
    <box frame="77" outside="0" occluded="0" keyframe="1" xtl="926.75" ytl="132.47" xbr="1080.47" ybr="388.95">
    </box>
    <box frame="78" outside="0" occluded="0" keyframe="1" xtl="918.41" ytl="133.99" xbr="1086.82" ybr="422.70">
    </box>
    <box frame="79" outside="0" occluded="0" keyframe="1" xtl="910.21" ytl="135.58" xbr="1092.65" ybr="458.86">
    </box>
    <box frame="86" outside="0" occluded="0" keyframe="1" xtl="906.46" ytl="130.24" xbr="1098.73" ybr="489.26">
    </box>
    <box frame="87" outside="0" occluded="0" keyframe="1" xtl="908.59" ytl="127.82" xbr="1095.40" ybr="492.06">
    </box>
    <box frame="88" outside="0" occluded="0" keyframe="1" xtl="910.71" ytl="125.14" xbr="1092.85" ybr="493.62">
    </box>
    <box frame="89" outside="0" occluded="0" keyframe="1" xtl="911.55" ytl="122.30" xbr="1090.88" ybr="496.70">
    </box>
    <box frame="90" outside="0" occluded="0" keyframe="1" xtl="913.21" ytl="119.53" xbr="1089.08" ybr="496.78">
    </box>
    <box frame="91" outside="0" occluded="0" keyframe="1" xtl="914.39" ytl="116.45" xbr="1087.58" ybr="497.07">
    </box>
    <box frame="92" outside="0" occluded="0" keyframe="1" xtl="914.10" ytl="112.99" xbr="1086.93" ybr="501.50">
    </box>
    <box frame="93" outside="0" occluded="0" keyframe="1" xtl="913.55" ytl="109.42" xbr="1086.12" ybr="505.14">
    </box>
    <box frame="94" outside="0" occluded="0" keyframe="1" xtl="911.62" ytl="106.70" xbr="1084.55" ybr="510.13">
    </box>
    <box frame="95" outside="0" occluded="0" keyframe="1" xtl="910.58" ytl="104.28" xbr="1081.37" ybr="508.12">
    </box>
    <box frame="96" outside="0" occluded="0" keyframe="1" xtl="916.86" ytl="101.98" xbr="1072.03" ybr="467.06">
    </box>
    <box frame="97" outside="0" occluded="0" keyframe="1" xtl="919.91" ytl="98.53" xbr="1065.30" ybr="436.70">
    </box>
    <box frame="98" outside="0" occluded="0" keyframe="1" xtl="915.39" ytl="95.54" xbr="1060.10" ybr="426.72">
    </box>
    <box frame="99" outside="0" occluded="0" keyframe="1" xtl="907.25" ytl="93.58" xbr="1053.72" ybr="421.21">
    </box>
    <box frame="100" outside="0" occluded="0" keyframe="1" xtl="886.25" ytl="91.04" xbr="1040.00" ybr="420.37">
    </box>
    <box frame="101" outside="0" occluded="0" keyframe="1" xtl="873.65" ytl="89.74" xbr="1034.44" ybr="422.21">
    </box>
    <box frame="102" outside="0" occluded="0" keyframe="1" xtl="866.50" ytl="89.76" xbr="1032.11" ybr="422.49">
    </box>
    <box frame="103" outside="0" occluded="0" keyframe="1" xtl="858.78" ytl="88.62" xbr="1032.97" ybr="431.85">
    </box>
    <box frame="104" outside="0" occluded="0" keyframe="1" xtl="854.26" ytl="88.63" xbr="1033.65" ybr="437.03">
    </box>
    <box frame="105" outside="0" occluded="0" keyframe="1" xtl="847.46" ytl="87.65" xbr="1034.07" ybr="447.95">
    </box>
    <box frame="106" outside="0" occluded="0" keyframe="1" xtl="842.16" ytl="87.49" xbr="1030.23" ybr="448.64">
    </box>
    <box frame="107" outside="0" occluded="0" keyframe="1" xtl="821.09" ytl="87.60" xbr="1044.73" ybr="524.98">
    </box>
    <box frame="108" outside="0" occluded="0" keyframe="1" xtl="803.07" ytl="86.35" xbr="1054.33" ybr="591.10">
    </box>
    <box frame="109" outside="0" occluded="0" keyframe="1" xtl="820.31" ytl="86.87" xbr="1029.41" ybr="502.12">
    </box>
    <box frame="110" outside="0" occluded="0" keyframe="1" xtl="824.28" ytl="87.12" xbr="1013.72" ybr="461.70">
    </box>
    <box frame="111" outside="0" occluded="0" keyframe="1" xtl="823.11" ytl="86.87" xbr="1005.73" ybr="446.83">
    </box>
    <box frame="112" outside="0" occluded="0" keyframe="1" xtl="820.63" ytl="85.51" xbr="1003.38" ybr="445.39">
    </box>
    <box frame="113" outside="0" occluded="0" keyframe="1" xtl="819.63" ytl="84.36" xbr="1000.40" ybr="439.48">
    </box>
    <box frame="114" outside="0" occluded="0" keyframe="1" xtl="772.74" ytl="82.08" xbr="1039.01" ybr="626.38">
    </box>
    <box frame="115" outside="0" occluded="0" keyframe="1" xtl="759.56" ytl="80.44" xbr="1046.73" ybr="689.20">
    </box>
    <box frame="116" outside="0" occluded="0" keyframe="1" xtl="753.21" ytl="79.06" xbr="1047.41" ybr="722.57">
    </box>
    <box frame="117" outside="0" occluded="0" keyframe="1" xtl="791.95" ytl="78.76" xbr="1018.81" ybr="570.18">
    </box>
    <box frame="118" outside="0" occluded="0" keyframe="1" xtl="809.34" ytl="79.09" xbr="1005.77" ybr="501.46">
    </box>
    <box frame="119" outside="0" occluded="0" keyframe="1" xtl="812.95" ytl="79.24" xbr="1003.25" ybr="486.62">
    </box>
    <box frame="120" outside="0" occluded="0" keyframe="1" xtl="814.58" ytl="79.15" xbr="1002.23" ybr="478.64">
    </box>
    <box frame="121" outside="0" occluded="0" keyframe="1" xtl="820.81" ytl="78.88" xbr="997.10" ybr="448.40">
    </box>
    <box frame="122" outside="0" occluded="0" keyframe="1" xtl="824.09" ytl="78.20" xbr="994.42" ybr="429.41">
    </box>
    <box frame="123" outside="0" occluded="0" keyframe="1" xtl="824.46" ytl="78.31" xbr="994.84" ybr="424.88">
    </box>
    <box frame="124" outside="0" occluded="0" keyframe="1" xtl="809.11" ytl="78.32" xbr="1010.60" ybr="493.44">
    </box>
    <box frame="125" outside="0" occluded="0" keyframe="1" xtl="799.85" ytl="78.11" xbr="1023.19" ybr="546.13">
    </box>
    <box frame="126" outside="0" occluded="0" keyframe="1" xtl="799.98" ytl="78.76" xbr="1030.96" ybr="568.72">
    </box>
    <box frame="127" outside="0" occluded="0" keyframe="1" xtl="802.52" ytl="78.78" xbr="1034.72" ybr="576.09">
    </box>
    <box frame="128" outside="0" occluded="0" keyframe="1" xtl="806.15" ytl="78.41" xbr="1039.02" ybr="580.72">
    </box>
  </track>
  <track id="5008" label="person">
    <box frame="119" outside="0" occluded="0" keyframe="1" xtl="781.09" ytl="77.31" xbr="1007.90" ybr="728.00">
    </box>
    <box frame="120" outside="1" occluded="0" keyframe="1" xtl="781.09" ytl="77.31" xbr="1007.90" ybr="728.00">
    </box>
  </track>
</annotations>
